swesarr_pytools/__init__.py
swesarr_pytools/access_swesarr.py
swesarr_pytools/common.py
swesarr_pytools/data_tools.py
swesarr_pytools/swesarr_pytools.py
swesarr_pytools/utils/__init__.py
swesarr_pytools/utils/helper.py
swesarr_pytools/utils/swesarr_utils.py
swesarr_pytools-0.1.11.dist-info/LICENSE
swesarr_pytools-0.1.11.dist-info/METADATA
swesarr_pytools-0.1.11.dist-info/WHEEL
swesarr_pytools-0.1.11.dist-info/entry_points.txt
swesarr_pytools-0.1.11.dist-info/top_level.txt
swesarr_pytools-0.1.11.dist-info/RECORD
