Metadata-Version: 2.1
Name: swesarr_pytools
Version: 0.1.11
Summary: Library for data retrieval and processing of NASA GSFC Snow Water Equivalent Synthetic Aperture Radar and Radiometer data.
Author-email: "Evi Ofekeze, Dylan R. Boyd and Hans-Peter Marshall" <eviofekeze@u.boisestate.edu>
License: MIT License
Project-URL: Homepage, https://github.com/eviofekeze/swesarr_pytools
Keywords: swesarr_pytools
Classifier: Intended Audience :: Developers
Classifier: Intended Audience :: Education
Classifier: Intended Audience :: Science/Research
Classifier: License :: OSI Approved :: MIT License
Classifier: Natural Language :: English
Classifier: Programming Language :: Python :: 3.8
Classifier: Programming Language :: Python :: 3.9
Classifier: Programming Language :: Python :: 3.10
Classifier: Programming Language :: Python :: 3.11
Classifier: Programming Language :: Python :: 3.12
Requires-Python: >=3.8
License-File: LICENSE
Requires-Dist: numpy
Requires-Dist: pytest
Requires-Dist: pandas
Requires-Dist: requests
Requires-Dist: rioxarray
Requires-Dist: xarray
Requires-Dist: geopy
Requires-Dist: beautifulsoup4
Provides-Extra: all
Requires-Dist: swesarr-pytools[extra] ; extra == 'all'
Provides-Extra: extra
Requires-Dist: pandas ; extra == 'extra'
